unstable_reader/__init__.py
unstable_reader/constants.py
unstable_reader/extractor.py
unstable_reader/image_data_reader.py
unstable_reader/utility.py
unstable_reader/format/__init__.py
unstable_reader/format/a1111.py
unstable_reader/format/base_format.py
unstable_reader/format/comfyui.py
unstable_reader/format/drawthings.py
unstable_reader/format/easydiffusion.py
unstable_reader/format/fooocus.py
unstable_reader/format/invokeai.py
unstable_reader/format/novelai.py
unstable_reader/format/swarmui.py
unstable_reader-0.1.0.dist-info/METADATA
unstable_reader-0.1.0.dist-info/WHEEL
unstable_reader-0.1.0.dist-info/top_level.txt
unstable_reader-0.1.0.dist-info/RECORD
