Metadata-Version: 2.1
Name: unstable_reader
Version: 0.1.0
Summary: A package to extract metadata from images generated by stable diffusion tools
Author: Markury
Author-email: github@markury.dev
Requires-Dist: piexif
Requires-Dist: Pillow
